pyegui-0.3.1.dist-info/METADATA
pyegui-0.3.1.dist-info/WHEEL
pyegui-0.3.1.dist-info/licenses/LICENSE
pyegui/__init__.py
pyegui/pyegui.pypy39-pp73-win_amd64.pyd
pyegui-0.3.1.dist-info/RECORD
