Metadata-Version: 2.4
Name: pyegui
Version: 0.3.1
Classifier: Operating System :: OS Independent
Classifier: License :: OSI Approved :: MIT License
Classifier: Programming Language :: Rust
Classifier: Programming Language :: Python :: Implementation :: CPython
Classifier: Programming Language :: Python :: Implementation :: PyPy
License-File: LICENSE
Summary: Immediate mode GUI library
Keywords: egui,GUI,imgui
Author: GachiLord
License: MIT
Requires-Python: >=3.11
Project-URL: Homepage, https://github.com/GachiLord/pyegui
Project-URL: Issues, https://github.com/GachiLord/pyegui/issues
